nostrmq/__init__.py
nostrmq/consumer.py
nostrmq/errors.py
nostrmq/nostrmq.py
nostrmq/producer.py
nostrmq/utils.py
package_name/__init__.py
package_name/package_name.py
nostrmq-0.2310.0.dist-info/LICENSE
nostrmq-0.2310.0.dist-info/METADATA
nostrmq-0.2310.0.dist-info/WHEEL
nostrmq-0.2310.0.dist-info/top_level.txt
nostrmq-0.2310.0.dist-info/RECORD
