Metadata-Version: 2.1
Name: nostrmq
Version: 0.2310.0
Summary: nostrmq
Home-page: https://github.com/labteral/nostrmq-python
Author: Rodrigo Martínez (brunneis)
Author-email: dev@brunneis.com
License: GNU General Public License v3 (GPLv3)
Platform: UNKNOWN
Classifier: Development Status :: 4 - Beta
Classifier: Environment :: Console
Classifier: Intended Audience :: Developers
Classifier: License :: OSI Approved :: GNU General Public License v3 (GPLv3)
Classifier: Operating System :: POSIX :: Linux
Classifier: Programming Language :: Python :: 3.10
Classifier: Programming Language :: Python :: Implementation :: PyPy
Classifier: Topic :: Software Development :: Libraries :: Python Modules
Requires-Python: >=3.10
License-File: LICENSE
Requires-Dist: nostr
